{"total_count": 1, "incomplete_results": false, "items": [{"url": "https://api.github.com/repos/PotatoSpudowski/fastLLaMa/issues/85", "repository_url": "https://api.github.com/repos/PotatoSpudowski/fastLLaMa", "labels_url": "https://api.github.com/repos/PotatoSpudowski/fastLLaMa/issues/85/labels{/name}", "comments_url": "https://api.github.com/repos/PotatoSpudowski/fastLLaMa/issues/85/comments", "events_url": "https://api.github.com/repos/PotatoSpudowski/fastLLaMa/issues/85/events", "html_url": "https://github.com/PotatoSpudowski/fastLLaMa/pull/85", "id": 1738417024, "node_id": "PR_kwDOJMfroc5SA66z", "number": 85, "title": "Add button to hide saves bar", "user": {"login": "stduhpf", "id": 28208228, "node_id": "MDQ6VXNlcjI4MjA4MjI4", "avatar_url": "https://avatars.githubusercontent.com/u/28208228?v=4", "gravatar_id": "", "url": "https://api.github.com/users/stduhpf", "html_url": "https://github.com/stduhpf", "followers_url": "https://api.github.com/users/stduhpf/followers", "following_url": "https://api.github.com/users/stduhpf/following{/other_user}", "gists_url": "https://api.github.com/users/stduhpf/gists{/gist_id}", "starred_url": "https://api.github.com/users/stduhpf/starred{/owner}{/repo}", "subscriptions_url": "https://api.github.com/users/stduhpf/subscriptions", "organizations_url": "https://api.github.com/users/stduhpf/orgs", "repos_url": "https://api.github.com/users/stduhpf/repos", "events_url": "https://api.github.com/users/stduhpf/events{/privacy}", "received_events_url": "https://api.github.com/users/stduhpf/received_events", "type": "User", "user_view_type": "public", "site_admin": false}, "labels": [], "state": "open", "locked": false, "assignee": null, "assignees": [], "milestone": null, "comments": 0, "created_at": "2023-06-02T15:34:53Z", "updated_at": "2023-06-02T22:28:37Z", "closed_at": null, "author_association": "CONTRIBUTOR", "sub_issues_summary": {"total": 0, "completed": 0, "percent_completed": 0}, "active_lock_reason": null, "draft": false, "pull_request": {"url": "https://api.github.com/repos/PotatoSpudowski/fastLLaMa/pulls/85", "html_url": "https://github.com/PotatoSpudowski/fastLLaMa/pull/85", "diff_url": "https://github.com/PotatoSpudowski/fastLLaMa/pull/85.diff", "patch_url": "https://github.com/PotatoSpudowski/fastLLaMa/pull/85.patch", "merged_at": null}, "body": "fixes https://github.com/PotatoSpudowski/fastLLaMa/issues/84.\r\nShould make the user experience much better when acessing the webui from a smartphone or a vertical monitor.", "reactions": {"url": "https://api.github.com/repos/PotatoSpudowski/fastLLaMa/issues/85/reactions", "total_count": 0, "+1": 0, "-1": 0, "laugh": 0, "hooray": 0, "confused": 0, "heart": 0, "rocket": 0, "eyes": 0}, "timeline_url": "https://api.github.com/repos/PotatoSpudowski/fastLLaMa/issues/85/timeline", "performed_via_github_app": null, "state_reason": null, "score": 1.0}]}