{"total_count": 1, "incomplete_results": false, "items": [{"url": "https://api.github.com/repos/JonathanSeals/locationfaker/issues/1", "repository_url": "https://api.github.com/repos/JonathanSeals/locationfaker", "labels_url": "https://api.github.com/repos/JonathanSeals/locationfaker/issues/1/labels{/name}", "comments_url": "https://api.github.com/repos/JonathanSeals/locationfaker/issues/1/comments", "events_url": "https://api.github.com/repos/JonathanSeals/locationfaker/issues/1/events", "html_url": "https://github.com/JonathanSeals/locationfaker/pull/1", "id": 676390804, "node_id": "MDExOlB1bGxSZXF1ZXN0NDY1NzEwMTUx", "number": 1, "title": "added the preferences controller + icon", "user": {"login": "dlevi309", "id": 7036054, "node_id": "MDQ6VXNlcjcwMzYwNTQ=", "avatar_url": "https://avatars.githubusercontent.com/u/7036054?v=4", "gravatar_id": "", "url": "https://api.github.com/users/dlevi309", "html_url": "https://github.com/dlevi309", "followers_url": "https://api.github.com/users/dlevi309/followers", "following_url": "https://api.github.com/users/dlevi309/following{/other_user}", "gists_url": "https://api.github.com/users/dlevi309/gists{/gist_id}", "starred_url": "https://api.github.com/users/dlevi309/starred{/owner}{/repo}", "subscriptions_url": "https://api.github.com/users/dlevi309/subscriptions", "organizations_url": "https://api.github.com/users/dlevi309/orgs", "repos_url": "https://api.github.com/users/dlevi309/repos", "events_url": "https://api.github.com/users/dlevi309/events{/privacy}", "received_events_url": "https://api.github.com/users/dlevi309/received_events", "type": "User", "user_view_type": "public", "site_admin": false}, "labels": [], "state": "open", "locked": false, "assignee": null, "assignees": [], "milestone": null, "comments": 0, "created_at": "2020-08-10T20:17:07Z", "updated_at": "2020-08-10T20:17:07Z", "closed_at": null, "author_association": "NONE", "sub_issues_summary": {"total": 0, "completed": 0, "percent_completed": 0}, "active_lock_reason": null, "draft": false, "pull_request": {"url": "https://api.github.com/repos/JonathanSeals/locationfaker/pulls/1", "html_url": "https://github.com/JonathanSeals/locationfaker/pull/1", "diff_url": "https://github.com/JonathanSeals/locationfaker/pull/1.diff", "patch_url": "https://github.com/JonathanSeals/locationfaker/pull/1.patch", "merged_at": null}, "body": "I wasn't sure if it was forgotten or not but I attempted to replicate the preference bundle as closely as possible to the released version.", "reactions": {"url": "https://api.github.com/repos/JonathanSeals/locationfaker/issues/1/reactions", "total_count": 0, "+1": 0, "-1": 0, "laugh": 0, "hooray": 0, "confused": 0, "heart": 0, "rocket": 0, "eyes": 0}, "timeline_url": "https://api.github.com/repos/JonathanSeals/locationfaker/issues/1/timeline", "performed_via_github_app": null, "state_reason": null, "score": 1.0}]}