{"login": "caikelun", "id": 102436, "node_id": "MDQ6VXNlcjEwMjQzNg==", "avatar_url": "https://avatars.githubusercontent.com/u/102436?v=4", "gravatar_id": "", "url": "https://api.github.com/users/caikelun", "html_url": "https://github.com/caikelun", "followers_url": "https://api.github.com/users/caikelun/followers", "following_url": "https://api.github.com/users/caikelun/following{/other_user}", "gists_url": "https://api.github.com/users/caikelun/gists{/gist_id}", "starred_url": "https://api.github.com/users/caikelun/starred{/owner}{/repo}", "subscriptions_url": "https://api.github.com/users/caikelun/subscriptions", "organizations_url": "https://api.github.com/users/caikelun/orgs", "repos_url": "https://api.github.com/users/caikelun/repos", "events_url": "https://api.github.com/users/caikelun/events{/privacy}", "received_events_url": "https://api.github.com/users/caikelun/received_events", "type": "User", "user_view_type": "public", "site_admin": false, "contributions": 94, "repository": "iqiyi/xCrash", "number": "5"}