{"id": 177474995, "node_id": "MDEwOlJlcG9zaXRvcnkxNzc0NzQ5OTU=", "name": "sudo_inject", "full_name": "nongiach/sudo_inject", "private": false, "owner": {"login": "nongiach", "id": 5711608, "node_id": "MDQ6VXNlcjU3MTE2MDg=", "avatar_url": "https://avatars.githubusercontent.com/u/5711608?v=4", "gravatar_id": "", "url": "https://api.github.com/users/nongiach", "html_url": "https://github.com/nongiach", "followers_url": "https://api.github.com/users/nongiach/followers", "following_url": "https://api.github.com/users/nongiach/following{/other_user}", "gists_url": "https://api.github.com/users/nongiach/gists{/gist_id}", "starred_url": "https://api.github.com/users/nongiach/starred{/owner}{/repo}", "subscriptions_url": "https://api.github.com/users/nongiach/subscriptions", "organizations_url": "https://api.github.com/users/nongiach/orgs", "repos_url": "https://api.github.com/users/nongiach/repos", "events_url": "https://api.github.com/users/nongiach/events{/privacy}", "received_events_url": "https://api.github.com/users/nongiach/received_events", "type": "User", "user_view_type": "public", "site_admin": false}, "html_url": "https://github.com/nongiach/sudo_inject", "description": "[Linux] Two Privilege Escalation techniques abusing sudo token", "fork": false, "url": "https://api.github.com/repos/nongiach/sudo_inject", "forks_url": "https://api.github.com/repos/nongiach/sudo_inject/forks", "keys_url": "https://api.github.com/repos/nongiach/sudo_inject/keys{/key_id}", "collaborators_url": "https://api.github.com/repos/nongiach/sudo_inject/collaborators{/collaborator}", "teams_url": "https://api.github.com/repos/nongiach/sudo_inject/teams", "hooks_url": "https://api.github.com/repos/nongiach/sudo_inject/hooks", "issue_events_url": "https://api.github.com/repos/nongiach/sudo_inject/issues/events{/number}", "events_url": "https://api.github.com/repos/nongiach/sudo_inject/events", "assignees_url": "https://api.github.com/repos/nongiach/sudo_inject/assignees{/user}", "branches_url": "https://api.github.com/repos/nongiach/sudo_inject/branches{/branch}", "tags_url": "https://api.github.com/repos/nongiach/sudo_inject/tags", "blobs_url": "https://api.github.com/repos/nongiach/sudo_inject/git/blobs{/sha}", "git_tags_url": "https://api.github.com/repos/nongiach/sudo_inject/git/tags{/sha}", "git_refs_url": "https://api.github.com/repos/nongiach/sudo_inject/git/refs{/sha}", "trees_url": "https://api.github.com/repos/nongiach/sudo_inject/git/trees{/sha}", "statuses_url": "https://api.github.com/repos/nongiach/sudo_inject/statuses/{sha}", "languages_url": "https://api.github.com/repos/nongiach/sudo_inject/languages", "stargazers_url": "https://api.github.com/repos/nongiach/sudo_inject/stargazers", "contributors_url": "https://api.github.com/repos/nongiach/sudo_inject/contributors", "subscribers_url": "https://api.github.com/repos/nongiach/sudo_inject/subscribers", "subscription_url": "https://api.github.com/repos/nongiach/sudo_inject/subscription", "commits_url": "https://api.github.com/repos/nongiach/sudo_inject/commits{/sha}", "git_commits_url": "https://api.github.com/repos/nongiach/sudo_inject/git/commits{/sha}", "comments_url": "https://api.github.com/repos/nongiach/sudo_inject/comments{/number}", "issue_comment_url": "https://api.github.com/repos/nongiach/sudo_inject/issues/comments{/number}", "contents_url": "https://api.github.com/repos/nongiach/sudo_inject/contents/{+path}", "compare_url": "https://api.github.com/repos/nongiach/sudo_inject/compare/{base}...{head}", "merges_url": "https://api.github.com/repos/nongiach/sudo_inject/merges", "archive_url": "https://api.github.com/repos/nongiach/sudo_inject/{archive_format}{/ref}", "downloads_url": "https://api.github.com/repos/nongiach/sudo_inject/downloads", "issues_url": "https://api.github.com/repos/nongiach/sudo_inject/issues{/number}", "pulls_url": "https://api.github.com/repos/nongiach/sudo_inject/pulls{/number}", "milestones_url": "https://api.github.com/repos/nongiach/sudo_inject/milestones{/number}", "notifications_url": "https://api.github.com/repos/nongiach/sudo_inject/notifications{?since,all,participating}", "labels_url": "https://api.github.com/repos/nongiach/sudo_inject/labels{/name}", "releases_url": "https://api.github.com/repos/nongiach/sudo_inject/releases{/id}", "deployments_url": "https://api.github.com/repos/nongiach/sudo_inject/deployments", "created_at": "2019-03-24T22:06:22Z", "updated_at": "2025-01-21T15:08:12Z", "pushed_at": "2019-04-14T07:43:35Z", "git_url": "git://github.com/nongiach/sudo_inject.git", "ssh_url": "git@github.com:nongiach/sudo_inject.git", "clone_url": "https://github.com/nongiach/sudo_inject.git", "svn_url": "https://github.com/nongiach/sudo_inject", "homepage": "", "size": 6130, "stargazers_count": 706, "watchers_count": 706, "language": "C", "has_issues": true, "has_projects": true, "has_downloads": true, "has_wiki": true, "has_pages": false, "has_discussions": false, "forks_count": 117, "mirror_url": null, "archived": false, "disabled": false, "open_issues_count": 1, "license": null, "allow_forking": true, "is_template": false, "web_commit_signoff_required": false, "topics": [], "visibility": "public", "forks": 117, "open_issues": 1, "watchers": 706, "default_branch": "master", "permissions": {"admin": false, "maintain": false, "push": false, "triage": false, "pull": true}, "temp_clone_token": "", "network_count": 117, "subscribers_count": 18}