{"sha": "c0d654736460d174a680b2e06c3a81ce883fc09a", "node_id": "C_kwDOE_X9-doAKGMwZDY1NDczNjQ2MGQxNzRhNjgwYjJlMDZjM2E4MWNlODgzZmMwOWE", "commit": {"author": {"name": "Tavis Ormandy", "email": "taviso@gmail.com", "date": "2022-05-01T21:29:31Z"}, "committer": {"name": "Tavis Ormandy", "email": "taviso@gmail.com", "date": "2022-05-01T21:29:31Z"}, "message": "subject missing re: for comments in XOVER", "tree": {"sha": "d91800e41de3cd0b93ee8de5cef2a387c67a22bf", "url": "https://api.github.com/repos/taviso/nntpit/git/trees/d91800e41de3cd0b93ee8de5cef2a387c67a22bf"}, "url": "https://api.github.com/repos/taviso/nntpit/git/commits/c0d654736460d174a680b2e06c3a81ce883fc09a", "comment_count": 0, "verification": {"verified": false, "reason": "unsigned", "signature": null, "payload": null, "verified_at": null}}, "url": "https://api.github.com/repos/taviso/nntpit/commits/c0d654736460d174a680b2e06c3a81ce883fc09a", "html_url": "https://github.com/taviso/nntpit/commit/c0d654736460d174a680b2e06c3a81ce883fc09a", "comments_url": "https://api.github.com/repos/taviso/nntpit/commits/c0d654736460d174a680b2e06c3a81ce883fc09a/comments", "author": {"login": "taviso", "id": 123814, "node_id": "MDQ6VXNlcjEyMzgxNA==", "avatar_url": "https://avatars.githubusercontent.com/u/123814?v=4", "gravatar_id": "", "url": "https://api.github.com/users/taviso", "html_url": "https://github.com/taviso", "followers_url": "https://api.github.com/users/taviso/followers", "following_url": "https://api.github.com/users/taviso/following{/other_user}", "gists_url": "https://api.github.com/users/taviso/gists{/gist_id}", "starred_url": "https://api.github.com/users/taviso/starred{/owner}{/repo}", "subscriptions_url": "https://api.github.com/users/taviso/subscriptions", "organizations_url": "https://api.github.com/users/taviso/orgs", "repos_url": "https://api.github.com/users/taviso/repos", "events_url": "https://api.github.com/users/taviso/events{/privacy}", "received_events_url": "https://api.github.com/users/taviso/received_events", "type": "User", "user_view_type": "public", "site_admin": false}, "committer": {"login": "taviso", "id": 123814, "node_id": "MDQ6VXNlcjEyMzgxNA==", "avatar_url": "https://avatars.githubusercontent.com/u/123814?v=4", "gravatar_id": "", "url": "https://api.github.com/users/taviso", "html_url": "https://github.com/taviso", "followers_url": "https://api.github.com/users/taviso/followers", "following_url": "https://api.github.com/users/taviso/following{/other_user}", "gists_url": "https://api.github.com/users/taviso/gists{/gist_id}", "starred_url": "https://api.github.com/users/taviso/starred{/owner}{/repo}", "subscriptions_url": "https://api.github.com/users/taviso/subscriptions", "organizations_url": "https://api.github.com/users/taviso/orgs", "repos_url": "https://api.github.com/users/taviso/repos", "events_url": "https://api.github.com/users/taviso/events{/privacy}", "received_events_url": "https://api.github.com/users/taviso/received_events", "type": "User", "user_view_type": "public", "site_admin": false}, "parents": [{"sha": "2cac8c3e13fbfd689be47dcb7749eb0b7a489123", "url": "https://api.github.com/repos/taviso/nntpit/commits/2cac8c3e13fbfd689be47dcb7749eb0b7a489123", "html_url": "https://github.com/taviso/nntpit/commit/2cac8c3e13fbfd689be47dcb7749eb0b7a489123"}], "repository": "taviso/nntpit", "number": "49"}