{"sha": "336be2d5bb2733f27e593dec70034a4f59650efd", "node_id": "C_kwDOKJv1mtoAKDMzNmJlMmQ1YmIyNzMzZjI3ZTU5M2RlYzcwMDM0YTRmNTk2NTBlZmQ", "commit": {"author": {"name": "Thomas SIMON", "email": "thomas.simon.work@gmail.com", "date": "2023-09-03T17:56:59Z"}, "committer": {"name": "Thomas SIMON", "email": "thomas.simon.work@gmail.com", "date": "2023-09-03T17:56:59Z"}, "message": "add macOS accelerator option", "tree": {"sha": "be1fa67186f495ac16e162dd5b9a9a96d902cef9", "url": "https://api.github.com/repos/Ruddle/Fomos/git/trees/be1fa67186f495ac16e162dd5b9a9a96d902cef9"}, "url": "https://api.github.com/repos/Ruddle/Fomos/git/commits/336be2d5bb2733f27e593dec70034a4f59650efd", "comment_count": 0, "verification": {"verified": false, "reason": "unsigned", "signature": null, "payload": null, "verified_at": null}}, "url": "https://api.github.com/repos/Ruddle/Fomos/commits/336be2d5bb2733f27e593dec70034a4f59650efd", "html_url": "https://github.com/Ruddle/Fomos/commit/336be2d5bb2733f27e593dec70034a4f59650efd", "comments_url": "https://api.github.com/repos/Ruddle/Fomos/commits/336be2d5bb2733f27e593dec70034a4f59650efd/comments", "author": {"login": "Ruddle", "id": 14235713, "node_id": "MDQ6VXNlcjE0MjM1NzEz", "avatar_url": "https://avatars.githubusercontent.com/u/14235713?v=4", "gravatar_id": "", "url": "https://api.github.com/users/Ruddle", "html_url": "https://github.com/Ruddle", "followers_url": "https://api.github.com/users/Ruddle/followers", "following_url": "https://api.github.com/users/Ruddle/following{/other_user}", "gists_url": "https://api.github.com/users/Ruddle/gists{/gist_id}", "starred_url": "https://api.github.com/users/Ruddle/starred{/owner}{/repo}", "subscriptions_url": "https://api.github.com/users/Ruddle/subscriptions", "organizations_url": "https://api.github.com/users/Ruddle/orgs", "repos_url": "https://api.github.com/users/Ruddle/repos", "events_url": "https://api.github.com/users/Ruddle/events{/privacy}", "received_events_url": "https://api.github.com/users/Ruddle/received_events", "type": "User", "user_view_type": "public", "site_admin": false}, "committer": {"login": "Ruddle", "id": 14235713, "node_id": "MDQ6VXNlcjE0MjM1NzEz", "avatar_url": "https://avatars.githubusercontent.com/u/14235713?v=4", "gravatar_id": "", "url": "https://api.github.com/users/Ruddle", "html_url": "https://github.com/Ruddle", "followers_url": "https://api.github.com/users/Ruddle/followers", "following_url": "https://api.github.com/users/Ruddle/following{/other_user}", "gists_url": "https://api.github.com/users/Ruddle/gists{/gist_id}", "starred_url": "https://api.github.com/users/Ruddle/starred{/owner}{/repo}", "subscriptions_url": "https://api.github.com/users/Ruddle/subscriptions", "organizations_url": "https://api.github.com/users/Ruddle/orgs", "repos_url": "https://api.github.com/users/Ruddle/repos", "events_url": "https://api.github.com/users/Ruddle/events{/privacy}", "received_events_url": "https://api.github.com/users/Ruddle/received_events", "type": "User", "user_view_type": "public", "site_admin": false}, "parents": [{"sha": "d12d5e7288ba62ae5be21b2b5e43b157f285a69c", "url": "https://api.github.com/repos/Ruddle/Fomos/commits/d12d5e7288ba62ae5be21b2b5e43b157f285a69c", "html_url": "https://github.com/Ruddle/Fomos/commit/d12d5e7288ba62ae5be21b2b5e43b157f285a69c"}], "repository": "Ruddle/Fomos", "number": "20"}