{"total_count": 14, "incomplete_results": false, "items": [{"url": "https://api.github.com/repos/rossimo/retrobot/issues/43", "repository_url": "https://api.github.com/repos/rossimo/retrobot", "labels_url": "https://api.github.com/repos/rossimo/retrobot/issues/43/labels{/name}", "comments_url": "https://api.github.com/repos/rossimo/retrobot/issues/43/comments", "events_url": "https://api.github.com/repos/rossimo/retrobot/issues/43/events", "html_url": "https://github.com/rossimo/retrobot/issues/43", "id": 1841049691, "node_id": "I_kwDOH4wTPs5tvDBb", "number": 43, "title": "Suggestion: Add the ability to download the current .sav from the channel", "user": {"login": "pedrotski", "id": 58076186, "node_id": "MDQ6VXNlcjU4MDc2MTg2", "avatar_url": "https://avatars.githubusercontent.com/u/58076186?v=4", "gravatar_id": "", "url": "https://api.github.com/users/pedrotski", "html_url": "https://github.com/pedrotski", "followers_url": "https://api.github.com/users/pedrotski/followers", "following_url": "https://api.github.com/users/pedrotski/following{/other_user}", "gists_url": "https://api.github.com/users/pedrotski/gists{/gist_id}", "starred_url": "https://api.github.com/users/pedrotski/starred{/owner}{/repo}", "subscriptions_url": "https://api.github.com/users/pedrotski/subscriptions", "organizations_url": "https://api.github.com/users/pedrotski/orgs", "repos_url": "https://api.github.com/users/pedrotski/repos", "events_url": "https://api.github.com/users/pedrotski/events{/privacy}", "received_events_url": "https://api.github.com/users/pedrotski/received_events", "type": "User", "user_view_type": "public", "site_admin": false}, "labels": [], "state": "closed", "locked": false, "assignee": null, "assignees": [], "milestone": null, "comments": 0, "created_at": "2023-08-08T10:39:41Z", "updated_at": "2023-12-15T09:21:47Z", "closed_at": "2023-12-15T09:21:47Z", "author_association": "NONE", "sub_issues_summary": {"total": 0, "completed": 0, "percent_completed": 0}, "active_lock_reason": null, "body": "This would be a nice feature for the bot to upload the current save state to the channel to players could continue their progress offline if they wish. Also it might be good for admins to be able to drag save states into the channel to be able to quickly load them up. \r\n\r\nThat would make pretty much everything be hands off from the cli", "reactions": {"url": "https://api.github.com/repos/rossimo/retrobot/issues/43/reactions", "total_count": 0, "+1": 0, "-1": 0, "laugh": 0, "hooray": 0, "confused": 0, "heart": 0, "rocket": 0, "eyes": 0}, "timeline_url": "https://api.github.com/repos/rossimo/retrobot/issues/43/timeline", "performed_via_github_app": null, "state_reason": "completed", "score": 1.0}]}