{"total_count": 2, "incomplete_results": false, "items": [{"url": "https://api.github.com/repos/thunlp/SE-WRL/issues/34", "repository_url": "https://api.github.com/repos/thunlp/SE-WRL", "labels_url": "https://api.github.com/repos/thunlp/SE-WRL/issues/34/labels{/name}", "comments_url": "https://api.github.com/repos/thunlp/SE-WRL/issues/34/comments", "events_url": "https://api.github.com/repos/thunlp/SE-WRL/issues/34/events", "html_url": "https://github.com/thunlp/SE-WRL/issues/34", "id": 1677654581, "node_id": "I_kwDOBUf58c5j_vo1", "number": 34, "title": "\u53ef\u4ee5\u516c\u5f00\u8bad\u7ec3\u597d\u7684word embedding\u6587\u4ef6\u5417", "user": {"login": "luoyueli", "id": 114631780, "node_id": "U_kgDOBtUkZA", "avatar_url": "https://avatars.githubusercontent.com/u/114631780?v=4", "gravatar_id": "", "url": "https://api.github.com/users/luoyueli", "html_url": "https://github.com/luoyueli", "followers_url": "https://api.github.com/users/luoyueli/followers", "following_url": "https://api.github.com/users/luoyueli/following{/other_user}", "gists_url": "https://api.github.com/users/luoyueli/gists{/gist_id}", "starred_url": "https://api.github.com/users/luoyueli/starred{/owner}{/repo}", "subscriptions_url": "https://api.github.com/users/luoyueli/subscriptions", "organizations_url": "https://api.github.com/users/luoyueli/orgs", "repos_url": "https://api.github.com/users/luoyueli/repos", "events_url": "https://api.github.com/users/luoyueli/events{/privacy}", "received_events_url": "https://api.github.com/users/luoyueli/received_events", "type": "User", "user_view_type": "public", "site_admin": false}, "labels": [], "state": "open", "locked": false, "assignee": null, "assignees": [], "milestone": null, "comments": 0, "created_at": "2023-04-21T02:06:24Z", "updated_at": "2023-04-21T02:06:24Z", "closed_at": null, "author_association": "NONE", "sub_issues_summary": {"total": 0, "completed": 0, "percent_completed": 0}, "active_lock_reason": null, "body": null, "reactions": {"url": "https://api.github.com/repos/thunlp/SE-WRL/issues/34/reactions", "total_count": 0, "+1": 0, "-1": 0, "laugh": 0, "hooray": 0, "confused": 0, "heart": 0, "rocket": 0, "eyes": 0}, "timeline_url": "https://api.github.com/repos/thunlp/SE-WRL/issues/34/timeline", "performed_via_github_app": null, "state_reason": null, "score": 1.0}]}