{"total_count": 77, "incomplete_results": false, "items": [{"url": "https://api.github.com/repos/yilozt/mutter-rounded/issues/123", "repository_url": "https://api.github.com/repos/yilozt/mutter-rounded", "labels_url": "https://api.github.com/repos/yilozt/mutter-rounded/issues/123/labels{/name}", "comments_url": "https://api.github.com/repos/yilozt/mutter-rounded/issues/123/comments", "events_url": "https://api.github.com/repos/yilozt/mutter-rounded/issues/123/events", "html_url": "https://github.com/yilozt/mutter-rounded/issues/123", "id": 2474202431, "node_id": "I_kwDOF-QBlc6TeVU_", "number": 123, "title": "[Question] Is there a way to blur the terminal?", "user": {"login": "AlwaysBorderRadius", "id": 116839018, "node_id": "U_kgDOBvbSag", "avatar_url": "https://avatars.githubusercontent.com/u/116839018?v=4", "gravatar_id": "", "url": "https://api.github.com/users/AlwaysBorderRadius", "html_url": "https://github.com/AlwaysBorderRadius", "followers_url": "https://api.github.com/users/AlwaysBorderRadius/followers", "following_url": "https://api.github.com/users/AlwaysBorderRadius/following{/other_user}", "gists_url": "https://api.github.com/users/AlwaysBorderRadius/gists{/gist_id}", "starred_url": "https://api.github.com/users/AlwaysBorderRadius/starred{/owner}{/repo}", "subscriptions_url": "https://api.github.com/users/AlwaysBorderRadius/subscriptions", "organizations_url": "https://api.github.com/users/AlwaysBorderRadius/orgs", "repos_url": "https://api.github.com/users/AlwaysBorderRadius/repos", "events_url": "https://api.github.com/users/AlwaysBorderRadius/events{/privacy}", "received_events_url": "https://api.github.com/users/AlwaysBorderRadius/received_events", "type": "User", "user_view_type": "public", "site_admin": false}, "labels": [], "state": "open", "locked": false, "assignee": null, "assignees": [], "milestone": null, "comments": 0, "created_at": "2024-08-19T21:03:42Z", "updated_at": "2024-08-19T21:03:42Z", "closed_at": null, "author_association": "NONE", "sub_issues_summary": {"total": 0, "completed": 0, "percent_completed": 0}, "active_lock_reason": null, "body": "I know this only works in Ubuntu 22.04 / Gnome 41 or lower and needs to be updated to work on the latests versions, but does the blurring part still work? if not, is there another way to blur my terminal? (I'm on Ubuntu 24.02 / Gnome 46)", "reactions": {"url": "https://api.github.com/repos/yilozt/mutter-rounded/issues/123/reactions", "total_count": 0, "+1": 0, "-1": 0, "laugh": 0, "hooray": 0, "confused": 0, "heart": 0, "rocket": 0, "eyes": 0}, "timeline_url": "https://api.github.com/repos/yilozt/mutter-rounded/issues/123/timeline", "performed_via_github_app": null, "state_reason": null, "score": 1.0}]}