{"total_count": 9, "incomplete_results": false, "items": [{"url": "https://api.github.com/repos/BLepers/KVell/issues/11", "repository_url": "https://api.github.com/repos/BLepers/KVell", "labels_url": "https://api.github.com/repos/BLepers/KVell/issues/11/labels{/name}", "comments_url": "https://api.github.com/repos/BLepers/KVell/issues/11/comments", "events_url": "https://api.github.com/repos/BLepers/KVell/issues/11/events", "html_url": "https://github.com/BLepers/KVell/issues/11", "id": 1473658223, "node_id": "I_kwDODGWEmM5X1j1v", "number": 11, "title": "About the YCSB+T benchmark", "user": {"login": "morcelicaio", "id": 21083525, "node_id": "MDQ6VXNlcjIxMDgzNTI1", "avatar_url": "https://avatars.githubusercontent.com/u/21083525?v=4", "gravatar_id": "", "url": "https://api.github.com/users/morcelicaio", "html_url": "https://github.com/morcelicaio", "followers_url": "https://api.github.com/users/morcelicaio/followers", "following_url": "https://api.github.com/users/morcelicaio/following{/other_user}", "gists_url": "https://api.github.com/users/morcelicaio/gists{/gist_id}", "starred_url": "https://api.github.com/users/morcelicaio/starred{/owner}{/repo}", "subscriptions_url": "https://api.github.com/users/morcelicaio/subscriptions", "organizations_url": "https://api.github.com/users/morcelicaio/orgs", "repos_url": "https://api.github.com/users/morcelicaio/repos", "events_url": "https://api.github.com/users/morcelicaio/events{/privacy}", "received_events_url": "https://api.github.com/users/morcelicaio/received_events", "type": "User", "user_view_type": "public", "site_admin": false}, "labels": [], "state": "open", "locked": false, "assignee": null, "assignees": [], "milestone": null, "comments": 5, "created_at": "2022-12-03T02:06:26Z", "updated_at": "2022-12-17T14:49:59Z", "closed_at": null, "author_association": "NONE", "sub_issues_summary": {"total": 0, "completed": 0, "percent_completed": 0}, "active_lock_reason": null, "body": "Hi, @BLepers .\r\n\r\nI have a question about the implementation of YCSB+T.\r\n\r\nWhere did you get the latest YCSB+T project?\r\n\r\nThe only place I can find to fork it is on Akon Dey's github.\r\nhttps://github.com/akon-dey/YCSB\r\n\r\nCould you help me to implement the ycsb+t benchmark correctly?\r\n\r\nIn his article he reports having such methods:\r\n\r\n\"\r\n\u2022 doTransactionInsert() creates a new account with an\r\ninitial balance captured from doTransactionDelete() operation described below.\r\n\r\n\u2022 doTransactionRead() reads a set of account balances\r\ndetermined by the key generator.\r\n\r\n\u2022 doTransactionScan() scans the database given the start\r\nkey and the number of records and fetches them from the\r\ndata base.\r\n\r\n\u2022 doTransactionUpdate() reads a record and add $1 from\r\nthe balance captured from delete operations to it and write\r\nit back.\r\n\r\n\u2022 doTransactionDelete() reads an account record, add the\r\namount to the captured the balance (capture used in\r\ndoTransactionInsert()) and then deletes the record.\r\n\r\n\u2022 doTransactionReadModifyWrite() reads two records,\r\nsubtracts $1 from the one of the two and adds $1 to\r\nthe other before writing them both back.\r\n\"\r\n\r\nIn the akon repository where I made the fork, I didn't find the implementation of the methods doTransactionInsert() , doTransactionRead() , doTransactionScan() , doTransactionUpdate() and doTransactionDelete().\r\n\r\nI just noticed that the doTransactionReadModifyWrite() method is implemented, where it subtracts the value 1 from account A and assigns that value to account B.\r\n\r\nCould you help me understand this part of the implementation?\r\n\r\nRegards,\r\nCaio", "reactions": {"url": "https://api.github.com/repos/BLepers/KVell/issues/11/reactions", "total_count": 0, "+1": 0, "-1": 0, "laugh": 0, "hooray": 0, "confused": 0, "heart": 0, "rocket": 0, "eyes": 0}, "timeline_url": "https://api.github.com/repos/BLepers/KVell/issues/11/timeline", "performed_via_github_app": null, "state_reason": null, "score": 1.0}]}