{"total_count": 4, "incomplete_results": false, "items": [{"url": "https://api.github.com/repos/0xkol/badspin/issues/15", "repository_url": "https://api.github.com/repos/0xkol/badspin", "labels_url": "https://api.github.com/repos/0xkol/badspin/issues/15/labels{/name}", "comments_url": "https://api.github.com/repos/0xkol/badspin/issues/15/comments", "events_url": "https://api.github.com/repos/0xkol/badspin/issues/15/events", "html_url": "https://github.com/0xkol/badspin/issues/15", "id": 2035393114, "node_id": "I_kwDOJNRCIs55UaJa", "number": 15, "title": "/data/data/ seems virtual", "user": {"login": "HasKarmi", "id": 153508096, "node_id": "U_kgDOCSZZAA", "avatar_url": "https://avatars.githubusercontent.com/u/153508096?v=4", "gravatar_id": "", "url": "https://api.github.com/users/HasKarmi", "html_url": "https://github.com/HasKarmi", "followers_url": "https://api.github.com/users/HasKarmi/followers", "following_url": "https://api.github.com/users/HasKarmi/following{/other_user}", "gists_url": "https://api.github.com/users/HasKarmi/gists{/gist_id}", "starred_url": "https://api.github.com/users/HasKarmi/starred{/owner}{/repo}", "subscriptions_url": "https://api.github.com/users/HasKarmi/subscriptions", "organizations_url": "https://api.github.com/users/HasKarmi/orgs", "repos_url": "https://api.github.com/users/HasKarmi/repos", "events_url": "https://api.github.com/users/HasKarmi/events{/privacy}", "received_events_url": "https://api.github.com/users/HasKarmi/received_events", "type": "User", "user_view_type": "public", "site_admin": false}, "labels": [], "state": "open", "locked": false, "assignee": null, "assignees": [], "milestone": null, "comments": 0, "created_at": "2023-12-11T10:52:46Z", "updated_at": "2023-12-11T10:52:46Z", "closed_at": null, "author_association": "NONE", "sub_issues_summary": {"total": 0, "completed": 0, "percent_completed": 0}, "active_lock_reason": null, "body": "Success and root, BUT\r\nthe /data/data directory seems like it's a virtual version, which has only my app, but not the rest of the apps, no packages present in it, as if this root has a different version in a different user-space or a container.\r\n\r\nHow is that possible?, and how to access or list the rest of the packages inside the /data/data/ directory ?", "reactions": {"url": "https://api.github.com/repos/0xkol/badspin/issues/15/reactions", "total_count": 0, "+1": 0, "-1": 0, "laugh": 0, "hooray": 0, "confused": 0, "heart": 0, "rocket": 0, "eyes": 0}, "timeline_url": "https://api.github.com/repos/0xkol/badspin/issues/15/timeline", "performed_via_github_app": null, "state_reason": null, "score": 1.0}]}