{"total_count": 4, "incomplete_results": false, "items": [{"url": "https://api.github.com/repos/cajakil/max-silent-dreams/issues/11", "repository_url": "https://api.github.com/repos/cajakil/max-silent-dreams", "labels_url": "https://api.github.com/repos/cajakil/max-silent-dreams/issues/11/labels{/name}", "comments_url": "https://api.github.com/repos/cajakil/max-silent-dreams/issues/11/comments", "events_url": "https://api.github.com/repos/cajakil/max-silent-dreams/issues/11/events", "html_url": "https://github.com/cajakil/max-silent-dreams/issues/11", "id": 2000408542, "node_id": "I_kwDOIVI2Ps53O8_e", "number": 11, "title": "SD_delayLaneTapOutComponent - can't stop reverse playing", "user": {"login": "cajakil", "id": 58376424, "node_id": "MDQ6VXNlcjU4Mzc2NDI0", "avatar_url": "https://avatars.githubusercontent.com/u/58376424?v=4", "gravatar_id": "", "url": "https://api.github.com/users/cajakil", "html_url": "https://github.com/cajakil", "followers_url": "https://api.github.com/users/cajakil/followers", "following_url": "https://api.github.com/users/cajakil/following{/other_user}", "gists_url": "https://api.github.com/users/cajakil/gists{/gist_id}", "starred_url": "https://api.github.com/users/cajakil/starred{/owner}{/repo}", "subscriptions_url": "https://api.github.com/users/cajakil/subscriptions", "organizations_url": "https://api.github.com/users/cajakil/orgs", "repos_url": "https://api.github.com/users/cajakil/repos", "events_url": "https://api.github.com/users/cajakil/events{/privacy}", "received_events_url": "https://api.github.com/users/cajakil/received_events", "type": "User", "user_view_type": "public", "site_admin": false}, "labels": [], "state": "open", "locked": false, "assignee": null, "assignees": [], "milestone": null, "comments": 0, "created_at": "2023-11-18T12:52:00Z", "updated_at": "2023-11-18T14:24:34Z", "closed_at": null, "author_association": "OWNER", "sub_issues_summary": {"total": 0, "completed": 0, "percent_completed": 0}, "active_lock_reason": null, "body": "introducing custom parameters breaks the delay playhead?\r\n\r\nhence the high one currently plays backwards and the other half can't be delayed", "reactions": {"url": "https://api.github.com/repos/cajakil/max-silent-dreams/issues/11/reactions", "total_count": 0, "+1": 0, "-1": 0, "laugh": 0, "hooray": 0, "confused": 0, "heart": 0, "rocket": 0, "eyes": 0}, "timeline_url": "https://api.github.com/repos/cajakil/max-silent-dreams/issues/11/timeline", "performed_via_github_app": null, "state_reason": null, "score": 1.0}]}