[{"login": "MarcoCouto", "id": 2512508, "node_id": "MDQ6VXNlcjI1MTI1MDg=", "avatar_url": "https://avatars.githubusercontent.com/u/2512508?v=4", "gravatar_id": "", "url": "https://api.github.com/users/MarcoCouto", "html_url": "https://github.com/MarcoCouto", "followers_url": "https://api.github.com/users/MarcoCouto/followers", "following_url": "https://api.github.com/users/MarcoCouto/following{/other_user}", "gists_url": "https://api.github.com/users/MarcoCouto/gists{/gist_id}", "starred_url": "https://api.github.com/users/MarcoCouto/starred{/owner}{/repo}", "subscriptions_url": "https://api.github.com/users/MarcoCouto/subscriptions", "organizations_url": "https://api.github.com/users/MarcoCouto/orgs", "repos_url": "https://api.github.com/users/MarcoCouto/repos", "events_url": "https://api.github.com/users/MarcoCouto/events{/privacy}", "received_events_url": "https://api.github.com/users/MarcoCouto/received_events", "type": "User", "user_view_type": "public", "site_admin": false, "contributions": 12}, {"login": "States", "id": 2579696, "node_id": "MDQ6VXNlcjI1Nzk2OTY=", "avatar_url": "https://avatars.githubusercontent.com/u/2579696?v=4", "gravatar_id": "", "url": "https://api.github.com/users/States", "html_url": "https://github.com/States", "followers_url": "https://api.github.com/users/States/followers", "following_url": "https://api.github.com/users/States/following{/other_user}", "gists_url": "https://api.github.com/users/States/gists{/gist_id}", "starred_url": "https://api.github.com/users/States/starred{/owner}{/repo}", "subscriptions_url": "https://api.github.com/users/States/subscriptions", "organizations_url": "https://api.github.com/users/States/orgs", "repos_url": "https://api.github.com/users/States/repos", "events_url": "https://api.github.com/users/States/events{/privacy}", "received_events_url": "https://api.github.com/users/States/received_events", "type": "User", "user_view_type": "public", "site_admin": false, "contributions": 4}, {"login": "ben-albrecht", "id": 3595449, "node_id": "MDQ6VXNlcjM1OTU0NDk=", "avatar_url": "https://avatars.githubusercontent.com/u/3595449?v=4", "gravatar_id": "", "url": "https://api.github.com/users/ben-albrecht", "html_url": "https://github.com/ben-albrecht", "followers_url": "https://api.github.com/users/ben-albrecht/followers", "following_url": "https://api.github.com/users/ben-albrecht/following{/other_user}", "gists_url": "https://api.github.com/users/ben-albrecht/gists{/gist_id}", "starred_url": "https://api.github.com/users/ben-albrecht/starred{/owner}{/repo}", "subscriptions_url": "https://api.github.com/users/ben-albrecht/subscriptions", "organizations_url": "https://api.github.com/users/ben-albrecht/orgs", "repos_url": "https://api.github.com/users/ben-albrecht/repos", "events_url": "https://api.github.com/users/ben-albrecht/events{/privacy}", "received_events_url": "https://api.github.com/users/ben-albrecht/received_events", "type": "User", "user_view_type": "public", "site_admin": false, "contributions": 1}, {"login": "felipemoz", "id": 60521463, "node_id": "MDQ6VXNlcjYwNTIxNDYz", "avatar_url": "https://avatars.githubusercontent.com/u/60521463?v=4", "gravatar_id": "", "url": "https://api.github.com/users/felipemoz", "html_url": "https://github.com/felipemoz", "followers_url": "https://api.github.com/users/felipemoz/followers", "following_url": "https://api.github.com/users/felipemoz/following{/other_user}", "gists_url": "https://api.github.com/users/felipemoz/gists{/gist_id}", "starred_url": "https://api.github.com/users/felipemoz/starred{/owner}{/repo}", "subscriptions_url": "https://api.github.com/users/felipemoz/subscriptions", "organizations_url": "https://api.github.com/users/felipemoz/orgs", "repos_url": "https://api.github.com/users/felipemoz/repos", "events_url": "https://api.github.com/users/felipemoz/events{/privacy}", "received_events_url": "https://api.github.com/users/felipemoz/received_events", "type": "User", "user_view_type": "public", "site_admin": false, "contributions": 1}, {"login": "zenunomacedo", "id": 17875932, "node_id": "MDQ6VXNlcjE3ODc1OTMy", "avatar_url": "https://avatars.githubusercontent.com/u/17875932?v=4", "gravatar_id": "", "url": "https://api.github.com/users/zenunomacedo", "html_url": "https://github.com/zenunomacedo", "followers_url": "https://api.github.com/users/zenunomacedo/followers", "following_url": "https://api.github.com/users/zenunomacedo/following{/other_user}", "gists_url": "https://api.github.com/users/zenunomacedo/gists{/gist_id}", "starred_url": "https://api.github.com/users/zenunomacedo/starred{/owner}{/repo}", "subscriptions_url": "https://api.github.com/users/zenunomacedo/subscriptions", "organizations_url": "https://api.github.com/users/zenunomacedo/orgs", "repos_url": "https://api.github.com/users/zenunomacedo/repos", "events_url": "https://api.github.com/users/zenunomacedo/events{/privacy}", "received_events_url": "https://api.github.com/users/zenunomacedo/received_events", "type": "User", "user_view_type": "public", "site_admin": false, "contributions": 1}, {"login": "logankilpatrick", "id": 35577566, "node_id": "MDQ6VXNlcjM1NTc3NTY2", "avatar_url": "https://avatars.githubusercontent.com/u/35577566?v=4", "gravatar_id": "", "url": "https://api.github.com/users/logankilpatrick", "html_url": "https://github.com/logankilpatrick", "followers_url": "https://api.github.com/users/logankilpatrick/followers", "following_url": "https://api.github.com/users/logankilpatrick/following{/other_user}", "gists_url": "https://api.github.com/users/logankilpatrick/gists{/gist_id}", "starred_url": "https://api.github.com/users/logankilpatrick/starred{/owner}{/repo}", "subscriptions_url": "https://api.github.com/users/logankilpatrick/subscriptions", "organizations_url": "https://api.github.com/users/logankilpatrick/orgs", "repos_url": "https://api.github.com/users/logankilpatrick/repos", "events_url": "https://api.github.com/users/logankilpatrick/events{/privacy}", "received_events_url": "https://api.github.com/users/logankilpatrick/received_events", "type": "User", "user_view_type": "public", "site_admin": false, "contributions": 1}, {"login": "meehew", "id": 45730044, "node_id": "MDQ6VXNlcjQ1NzMwMDQ0", "avatar_url": "https://avatars.githubusercontent.com/u/45730044?v=4", "gravatar_id": "", "url": "https://api.github.com/users/meehew", "html_url": "https://github.com/meehew", "followers_url": "https://api.github.com/users/meehew/followers", "following_url": "https://api.github.com/users/meehew/following{/other_user}", "gists_url": "https://api.github.com/users/meehew/gists{/gist_id}", "starred_url": "https://api.github.com/users/meehew/starred{/owner}{/repo}", "subscriptions_url": "https://api.github.com/users/meehew/subscriptions", "organizations_url": "https://api.github.com/users/meehew/orgs", "repos_url": "https://api.github.com/users/meehew/repos", "events_url": "https://api.github.com/users/meehew/events{/privacy}", "received_events_url": "https://api.github.com/users/meehew/received_events", "type": "User", "user_view_type": "public", "site_admin": false, "contributions": 1}]