[{"login": "zhengthomastang", "id": 15898768, "node_id": "MDQ6VXNlcjE1ODk4NzY4", "avatar_url": "https://avatars.githubusercontent.com/u/15898768?v=4", "gravatar_id": "", "url": "https://api.github.com/users/zhengthomastang", "html_url": "https://github.com/zhengthomastang", "followers_url": "https://api.github.com/users/zhengthomastang/followers", "following_url": "https://api.github.com/users/zhengthomastang/following{/other_user}", "gists_url": "https://api.github.com/users/zhengthomastang/gists{/gist_id}", "starred_url": "https://api.github.com/users/zhengthomastang/starred{/owner}{/repo}", "subscriptions_url": "https://api.github.com/users/zhengthomastang/subscriptions", "organizations_url": "https://api.github.com/users/zhengthomastang/orgs", "repos_url": "https://api.github.com/users/zhengthomastang/repos", "events_url": "https://api.github.com/users/zhengthomastang/events{/privacy}", "received_events_url": "https://api.github.com/users/zhengthomastang/received_events", "type": "User", "user_view_type": "public", "site_admin": false, "contributions": 76}, {"login": "AlexXiao95", "id": 16890489, "node_id": "MDQ6VXNlcjE2ODkwNDg5", "avatar_url": "https://avatars.githubusercontent.com/u/16890489?v=4", "gravatar_id": "", "url": "https://api.github.com/users/AlexXiao95", "html_url": "https://github.com/AlexXiao95", "followers_url": "https://api.github.com/users/AlexXiao95/followers", "following_url": "https://api.github.com/users/AlexXiao95/following{/other_user}", "gists_url": "https://api.github.com/users/AlexXiao95/gists{/gist_id}", "starred_url": "https://api.github.com/users/AlexXiao95/starred{/owner}{/repo}", "subscriptions_url": "https://api.github.com/users/AlexXiao95/subscriptions", "organizations_url": "https://api.github.com/users/AlexXiao95/orgs", "repos_url": "https://api.github.com/users/AlexXiao95/repos", "events_url": "https://api.github.com/users/AlexXiao95/events{/privacy}", "received_events_url": "https://api.github.com/users/AlexXiao95/received_events", "type": "User", "user_view_type": "public", "site_admin": false, "contributions": 9}]