{"login": "adamsvoboda", "id": 3341597, "node_id": "MDQ6VXNlcjMzNDE1OTc=", "avatar_url": "https://avatars.githubusercontent.com/u/3341597?v=4", "gravatar_id": "", "url": "https://api.github.com/users/adamsvoboda", "html_url": "https://github.com/adamsvoboda", "followers_url": "https://api.github.com/users/adamsvoboda/followers", "following_url": "https://api.github.com/users/adamsvoboda/following{/other_user}", "gists_url": "https://api.github.com/users/adamsvoboda/gists{/gist_id}", "starred_url": "https://api.github.com/users/adamsvoboda/starred{/owner}{/repo}", "subscriptions_url": "https://api.github.com/users/adamsvoboda/subscriptions", "organizations_url": "https://api.github.com/users/adamsvoboda/orgs", "repos_url": "https://api.github.com/users/adamsvoboda/repos", "events_url": "https://api.github.com/users/adamsvoboda/events{/privacy}", "received_events_url": "https://api.github.com/users/adamsvoboda/received_events", "type": "User", "user_view_type": "public", "site_admin": false, "name": "Adam Svoboda", "company": null, "blog": "https://adamsvoboda.net", "location": null, "email": null, "hireable": null, "bio": null, "twitter_username": "adamsvoboda", "public_repos": 22, "public_gists": 5, "followers": 126, "following": 115, "created_at": "2013-01-22T17:09:29Z", "updated_at": "2025-01-23T16:58:58Z"}