{"login": "GeoSn0w", "id": 15067741, "node_id": "MDQ6VXNlcjE1MDY3NzQx", "avatar_url": "https://avatars.githubusercontent.com/u/15067741?v=4", "gravatar_id": "", "url": "https://api.github.com/users/GeoSn0w", "html_url": "https://github.com/GeoSn0w", "followers_url": "https://api.github.com/users/GeoSn0w/followers", "following_url": "https://api.github.com/users/GeoSn0w/following{/other_user}", "gists_url": "https://api.github.com/users/GeoSn0w/gists{/gist_id}", "starred_url": "https://api.github.com/users/GeoSn0w/starred{/owner}{/repo}", "subscriptions_url": "https://api.github.com/users/GeoSn0w/subscriptions", "organizations_url": "https://api.github.com/users/GeoSn0w/orgs", "repos_url": "https://api.github.com/users/GeoSn0w/repos", "events_url": "https://api.github.com/users/GeoSn0w/events{/privacy}", "received_events_url": "https://api.github.com/users/GeoSn0w/received_events", "type": "User", "user_view_type": "public", "site_admin": false, "name": "GeoSn0w", "company": "iDevice Central", "blog": "https://idevicecentral.com", "location": "Italy", "email": null, "hireable": true, "bio": "Programmer, Interested in INFOSEC. I like to tinker with iOS and Android. Interested in iOS Security and Malware disassembly", "twitter_username": "FCE365", "public_repos": 150, "public_gists": 3, "followers": 1409, "following": 35, "created_at": "2015-10-10T19:02:18Z", "updated_at": "2024-12-17T15:10:19Z"}