{"login": "gkurz", "id": 7049625, "node_id": "MDQ6VXNlcjcwNDk2MjU=", "avatar_url": "https://avatars.githubusercontent.com/u/7049625?v=4", "gravatar_id": "", "url": "https://api.github.com/users/gkurz", "html_url": "https://github.com/gkurz", "followers_url": "https://api.github.com/users/gkurz/followers", "following_url": "https://api.github.com/users/gkurz/following{/other_user}", "gists_url": "https://api.github.com/users/gkurz/gists{/gist_id}", "starred_url": "https://api.github.com/users/gkurz/starred{/owner}{/repo}", "subscriptions_url": "https://api.github.com/users/gkurz/subscriptions", "organizations_url": "https://api.github.com/users/gkurz/orgs", "repos_url": "https://api.github.com/users/gkurz/repos", "events_url": "https://api.github.com/users/gkurz/events{/privacy}", "received_events_url": "https://api.github.com/users/gkurz/received_events", "type": "User", "user_view_type": "public", "site_admin": false, "name": "Greg Kurz", "company": "Red Hat", "blog": "", "location": "Toulouse, France", "email": "groug@kaod.org", "hireable": null, "bio": null, "twitter_username": null, "public_repos": 22, "public_gists": 2, "followers": 13, "following": 22, "created_at": "2014-03-24T16:55:34Z", "updated_at": "2025-01-31T10:00:28Z"}