{"login": "JonaLoeffler", "id": 37999659, "node_id": "MDQ6VXNlcjM3OTk5NjU5", "avatar_url": "https://avatars.githubusercontent.com/u/37999659?v=4", "gravatar_id": "", "url": "https://api.github.com/users/JonaLoeffler", "html_url": "https://github.com/JonaLoeffler", "followers_url": "https://api.github.com/users/JonaLoeffler/followers", "following_url": "https://api.github.com/users/JonaLoeffler/following{/other_user}", "gists_url": "https://api.github.com/users/JonaLoeffler/gists{/gist_id}", "starred_url": "https://api.github.com/users/JonaLoeffler/starred{/owner}{/repo}", "subscriptions_url": "https://api.github.com/users/JonaLoeffler/subscriptions", "organizations_url": "https://api.github.com/users/JonaLoeffler/orgs", "repos_url": "https://api.github.com/users/JonaLoeffler/repos", "events_url": "https://api.github.com/users/JonaLoeffler/events{/privacy}", "received_events_url": "https://api.github.com/users/JonaLoeffler/received_events", "type": "User", "user_view_type": "public", "site_admin": false, "name": "Jona L\u00f6ffler", "company": null, "blog": "", "location": "Koblenz, Germany", "email": null, "hireable": null, "bio": null, "twitter_username": null, "public_repos": 20, "public_gists": 0, "followers": 1, "following": 0, "created_at": "2018-04-02T08:35:41Z", "updated_at": "2025-01-22T09:19:05Z"}