{"login": "MarcoCouto", "id": 2512508, "node_id": "MDQ6VXNlcjI1MTI1MDg=", "avatar_url": "https://avatars.githubusercontent.com/u/2512508?v=4", "gravatar_id": "", "url": "https://api.github.com/users/MarcoCouto", "html_url": "https://github.com/MarcoCouto", "followers_url": "https://api.github.com/users/MarcoCouto/followers", "following_url": "https://api.github.com/users/MarcoCouto/following{/other_user}", "gists_url": "https://api.github.com/users/MarcoCouto/gists{/gist_id}", "starred_url": "https://api.github.com/users/MarcoCouto/starred{/owner}{/repo}", "subscriptions_url": "https://api.github.com/users/MarcoCouto/subscriptions", "organizations_url": "https://api.github.com/users/MarcoCouto/orgs", "repos_url": "https://api.github.com/users/MarcoCouto/repos", "events_url": "https://api.github.com/users/MarcoCouto/events{/privacy}", "received_events_url": "https://api.github.com/users/MarcoCouto/received_events", "type": "User", "user_view_type": "public", "site_admin": false, "name": "Marco Couto", "company": null, "blog": "", "location": null, "email": null, "hireable": null, "bio": null, "twitter_username": null, "public_repos": 8, "public_gists": 0, "followers": 4, "following": 6, "created_at": "2012-10-08T15:02:17Z", "updated_at": "2024-11-20T22:58:02Z"}