{"login": "mlouielu", "id": 28770408, "node_id": "MDQ6VXNlcjI4NzcwNDA4", "avatar_url": "https://avatars.githubusercontent.com/u/28770408?v=4", "gravatar_id": "", "url": "https://api.github.com/users/mlouielu", "html_url": "https://github.com/mlouielu", "followers_url": "https://api.github.com/users/mlouielu/followers", "following_url": "https://api.github.com/users/mlouielu/following{/other_user}", "gists_url": "https://api.github.com/users/mlouielu/gists{/gist_id}", "starred_url": "https://api.github.com/users/mlouielu/starred{/owner}{/repo}", "subscriptions_url": "https://api.github.com/users/mlouielu/subscriptions", "organizations_url": "https://api.github.com/users/mlouielu/orgs", "repos_url": "https://api.github.com/users/mlouielu/repos", "events_url": "https://api.github.com/users/mlouielu/events{/privacy}", "received_events_url": "https://api.github.com/users/mlouielu/received_events", "type": "User", "user_view_type": "public", "site_admin": false, "name": "Louie Lu", "company": null, "blog": "https://louie.lu", "location": "Taiwan", "email": "git@louie.lu", "hireable": true, "bio": "PGP (current): 41D9 6FA4 C015 35B2 9ED4  ED8B 9707 2A25 D5BB 7392\r\n\r\n\r\n---\r\nPGP (old): --47B1 6C52 6E11 C03C B572  8CAD EF1F 3298 7A79 D5AE--", "twitter_username": null, "public_repos": 161, "public_gists": 39, "followers": 247, "following": 4, "created_at": "2017-05-18T02:46:39Z", "updated_at": "2025-01-25T05:09:05Z"}