{"login": "supriyar", "id": 2657489, "node_id": "MDQ6VXNlcjI2NTc0ODk=", "avatar_url": "https://avatars.githubusercontent.com/u/2657489?v=4", "gravatar_id": "", "url": "https://api.github.com/users/supriyar", "html_url": "https://github.com/supriyar", "followers_url": "https://api.github.com/users/supriyar/followers", "following_url": "https://api.github.com/users/supriyar/following{/other_user}", "gists_url": "https://api.github.com/users/supriyar/gists{/gist_id}", "starred_url": "https://api.github.com/users/supriyar/starred{/owner}{/repo}", "subscriptions_url": "https://api.github.com/users/supriyar/subscriptions", "organizations_url": "https://api.github.com/users/supriyar/orgs", "repos_url": "https://api.github.com/users/supriyar/repos", "events_url": "https://api.github.com/users/supriyar/events{/privacy}", "received_events_url": "https://api.github.com/users/supriyar/received_events", "type": "User", "user_view_type": "public", "site_admin": false, "name": null, "company": "@facebook", "blog": "", "location": null, "email": null, "hireable": null, "bio": null, "twitter_username": null, "public_repos": 13, "public_gists": 4, "followers": 16, "following": 0, "created_at": "2012-10-26T13:50:03Z", "updated_at": "2024-09-05T15:21:55Z"}