{"login": "Vloupmon", "id": 6957532, "node_id": "MDQ6VXNlcjY5NTc1MzI=", "avatar_url": "https://avatars.githubusercontent.com/u/6957532?v=4", "gravatar_id": "", "url": "https://api.github.com/users/Vloupmon", "html_url": "https://github.com/Vloupmon", "followers_url": "https://api.github.com/users/Vloupmon/followers", "following_url": "https://api.github.com/users/Vloupmon/following{/other_user}", "gists_url": "https://api.github.com/users/Vloupmon/gists{/gist_id}", "starred_url": "https://api.github.com/users/Vloupmon/starred{/owner}{/repo}", "subscriptions_url": "https://api.github.com/users/Vloupmon/subscriptions", "organizations_url": "https://api.github.com/users/Vloupmon/orgs", "repos_url": "https://api.github.com/users/Vloupmon/repos", "events_url": "https://api.github.com/users/Vloupmon/events{/privacy}", "received_events_url": "https://api.github.com/users/Vloupmon/received_events", "type": "User", "user_view_type": "public", "site_admin": false, "name": "Vincent Loupmon", "company": null, "blog": "", "location": "Aix-en-Provence, France", "email": null, "hireable": null, "bio": "YAML merchant.", "twitter_username": null, "public_repos": 13, "public_gists": 0, "followers": 12, "following": 6, "created_at": "2014-03-15T05:21:27Z", "updated_at": "2025-01-29T13:20:11Z"}